pybondmachine/__init__.py
pybondmachine/converters/__init__.py
pybondmachine/converters/pytorch2bm.py
pybondmachine/converters/tensorflow2bm.py
pybondmachine/overlay/__init__.py
pybondmachine/overlay/aximmhandler.py
pybondmachine/overlay/axisthandler.py
pybondmachine/overlay/predictor.py
pybondmachine/prjmanager/__init__.py
pybondmachine/prjmanager/neuralnetwork.py
pybondmachine/prjmanager/prjhandler.py
pybondmachine-1.1.74.dist-info/METADATA
pybondmachine-1.1.74.dist-info/WHEEL
pybondmachine-1.1.74.dist-info/entry_points.txt
pybondmachine-1.1.74.dist-info/top_level.txt
pybondmachine-1.1.74.dist-info/RECORD
