Metadata-Version: 2.1
Name: pybondmachine
Version: 1.1.74
Summary: pybondmachine is the Python library designed to streamline the development of FPGA accelerators through the use of the BondMachine framework.
Home-page: UNKNOWN
Author: Giulio Bianchini
Author-email: gibianch@pg.infn.it
License: UNKNOWN
Platform: UNKNOWN
